odoo10_addon_base_import_odoo-10.0.1.0.0.99.dev7-py3.8-nspkg.pth
odoo/addons/base_import_odoo/CONFIGURE.rst
odoo/addons/base_import_odoo/CONTRIBUTORS.rst
odoo/addons/base_import_odoo/DESCRIPTION.rst
odoo/addons/base_import_odoo/README.rst
odoo/addons/base_import_odoo/ROADMAP.rst
odoo/addons/base_import_odoo/USAGE.rst
odoo/addons/base_import_odoo/__init__.py
odoo/addons/base_import_odoo/__manifest__.py
odoo/addons/base_import_odoo/demo/import_odoo_database.xml
odoo/addons/base_import_odoo/demo/import_odoo_database_field.xml
odoo/addons/base_import_odoo/demo/import_odoo_database_model.xml
odoo/addons/base_import_odoo/demo/ir_attachment.xml
odoo/addons/base_import_odoo/demo/res_partner.xml
odoo/addons/base_import_odoo/demo/res_users.xml
odoo/addons/base_import_odoo/i18n/am.po
odoo/addons/base_import_odoo/i18n/ar.po
odoo/addons/base_import_odoo/i18n/base_import_odoo.pot
odoo/addons/base_import_odoo/i18n/bg.po
odoo/addons/base_import_odoo/i18n/bs.po
odoo/addons/base_import_odoo/i18n/ca.po
odoo/addons/base_import_odoo/i18n/ca_ES.po
odoo/addons/base_import_odoo/i18n/cs.po
odoo/addons/base_import_odoo/i18n/da.po
odoo/addons/base_import_odoo/i18n/da_DK.po
odoo/addons/base_import_odoo/i18n/de.po
odoo/addons/base_import_odoo/i18n/el_GR.po
odoo/addons/base_import_odoo/i18n/en_GB.po
odoo/addons/base_import_odoo/i18n/es.po
odoo/addons/base_import_odoo/i18n/es_AR.po
odoo/addons/base_import_odoo/i18n/es_CL.po
odoo/addons/base_import_odoo/i18n/es_CO.po
odoo/addons/base_import_odoo/i18n/es_CR.po
odoo/addons/base_import_odoo/i18n/es_DO.po
odoo/addons/base_import_odoo/i18n/es_EC.po
odoo/addons/base_import_odoo/i18n/es_ES.po
odoo/addons/base_import_odoo/i18n/es_MX.po
odoo/addons/base_import_odoo/i18n/es_PE.po
odoo/addons/base_import_odoo/i18n/es_PY.po
odoo/addons/base_import_odoo/i18n/es_VE.po
odoo/addons/base_import_odoo/i18n/et.po
odoo/addons/base_import_odoo/i18n/eu.po
odoo/addons/base_import_odoo/i18n/fa.po
odoo/addons/base_import_odoo/i18n/fi.po
odoo10_addon_base_import_odoo-10.0.1.0.0.99.dev7.dist-info/METADATA
odoo10_addon_base_import_odoo-10.0.1.0.0.99.dev7.dist-info/WHEEL
odoo10_addon_base_import_odoo-10.0.1.0.0.99.dev7.dist-info/namespace_packages.txt
odoo10_addon_base_import_odoo-10.0.1.0.0.99.dev7.dist-info/top_level.txt
odoo10_addon_base_import_odoo-10.0.1.0.0.99.dev7.dist-info/RECORD
